stripe_invoice_bot/__init__.py
stripe_invoice_bot/main.py
stripe_invoice_bot-0.0.2.dist-info/METADATA
stripe_invoice_bot-0.0.2.dist-info/WHEEL
stripe_invoice_bot-0.0.2.dist-info/entry_points.txt
stripe_invoice_bot-0.0.2.dist-info/top_level.txt
stripe_invoice_bot-0.0.2.dist-info/RECORD
