Metadata-Version: 2.1
Name: stripe-invoice-bot
Version: 0.0.2
Summary: Discord bot to create customers and generate invoices
Home-page: https://github.com/jmarhee/stripe-invoice-bot
Author: jmarhee
Author-email: jmarhee@interiorae.com
License: MIT
Platform: UNKNOWN
Requires-Python: >=3.6
Requires-Dist: discord
Requires-Dist: stripe
Requires-Dist: tabulate
